OdenGraphQt/__init__.py
OdenGraphQt/constants.py
OdenGraphQt/errors.py
OdenGraphQt/pkg_info.py
OdenGraphQt/base/__init__.py
OdenGraphQt/base/commands.py
OdenGraphQt/base/factory.py
OdenGraphQt/base/graph.py
OdenGraphQt/base/menu.py
OdenGraphQt/base/model.py
OdenGraphQt/base/node.py
OdenGraphQt/base/port.py
OdenGraphQt/base/types.py
OdenGraphQt/custom_widgets/__init__.py
OdenGraphQt/custom_widgets/nodes_palette.py
OdenGraphQt/custom_widgets/nodes_tree.py
OdenGraphQt/custom_widgets/properties_bin/__init__.py
OdenGraphQt/custom_widgets/properties_bin/custom_widget_color_picker.py
OdenGraphQt/custom_widgets/properties_bin/custom_widget_extra.py
OdenGraphQt/custom_widgets/properties_bin/custom_widget_file_paths.py
OdenGraphQt/custom_widgets/properties_bin/custom_widget_slider.py
OdenGraphQt/custom_widgets/properties_bin/custom_widget_value_edit.py
OdenGraphQt/custom_widgets/properties_bin/custom_widget_vectors.py
OdenGraphQt/custom_widgets/properties_bin/node_property_factory.py
OdenGraphQt/custom_widgets/properties_bin/node_property_widgets.py
OdenGraphQt/custom_widgets/properties_bin/prop_widgets_abstract.py
OdenGraphQt/custom_widgets/properties_bin/prop_widgets_base.py
OdenGraphQt/nodes/__init__.py
OdenGraphQt/nodes/backdrop_node.py
OdenGraphQt/nodes/base_node.py
OdenGraphQt/nodes/base_node_circle.py
OdenGraphQt/nodes/group_node.py
OdenGraphQt/nodes/port_node.py
OdenGraphQt/qgraphics/__init__.py
OdenGraphQt/qgraphics/node_abstract.py
OdenGraphQt/qgraphics/node_backdrop.py
OdenGraphQt/qgraphics/node_base.py
OdenGraphQt/qgraphics/node_circle.py
OdenGraphQt/qgraphics/node_group.py
OdenGraphQt/qgraphics/node_overlay_disabled.py
OdenGraphQt/qgraphics/node_port_in.py
OdenGraphQt/qgraphics/node_port_out.py
OdenGraphQt/qgraphics/node_text_item.py
OdenGraphQt/qgraphics/pipe.py
OdenGraphQt/qgraphics/port.py
OdenGraphQt/qgraphics/slicer.py
OdenGraphQt/widgets/__init__.py
OdenGraphQt/widgets/actions.py
OdenGraphQt/widgets/dialogs.py
OdenGraphQt/widgets/node_graph.py
OdenGraphQt-0.7.4.dist-info/LICENSE.md
OdenGraphQt-0.7.4.dist-info/METADATA
OdenGraphQt-0.7.4.dist-info/WHEEL
OdenGraphQt-0.7.4.dist-info/top_level.txt
OdenGraphQt-0.7.4.dist-info/RECORD
