Metadata-Version: 2.1
Name: OdenGraphQt
Version: 0.7.4
Summary: Node graph framework for PySide6/PyQt6 that can be implemented and re-purposed into applications.
Author: Huey Yeng, Johnny Chan
Maintainer: Huey Yeng
License: MIT License
Project-URL: Homepage, https://github.com/hueyyeng/OdenGraphQt
Project-URL: Bug Reports, https://github.com/hueyyeng/OdenGraphQt/issues
Project-URL: Source, https://github.com/hueyyeng/OdenGraphQt
Keywords: python,library,qt,widgets,development
Classifier: Intended Audience :: Developers
Classifier: Operating System :: OS Independent
Classifier: License :: OSI Approved :: MIT License
Classifier: Programming Language :: Python :: 3.11
Classifier: Programming Language :: Python :: 3.10
Classifier: Programming Language :: Python :: 3.9
Classifier: Programming Language :: Python :: 3.8
Requires-Python: >=3.8
License-File: LICENSE.md
Requires-Dist: typing-extensions >=4.9.0
Requires-Dist: PySide6 >=6.5.0
Requires-Dist: qtpy >=2.3.1
